Metadata-Version: 2.1
Name: odoo-addon-pos_session_pay_invoice
Version: 16.0.1.0.3.2
Summary: Pay and receive invoices from PoS Session
Home-page: https://github.com/OCA/pos
Author: Creu Blanca, Odoo Community Association (OCA)
Author-email: support@odoo-community.org
License: LGPL-3
Classifier: Programming Language :: Python
Classifier: Framework :: Odoo
Classifier: Framework :: Odoo :: 16.0
Classifier: License :: OSI Approved :: GNU Lesser General Public License v3 (LGPLv3)
Requires-Python: >=3.10
Requires-Dist: odoo-addon-account-cash-invoice<16.1dev,>=16.0dev
Requires-Dist: odoo<16.1dev,>=16.0a
